debts/__init__.py
debts/cli.py
debts/solver.py
debts/renderers/__init__.py
debts/renderers/html.py
debts/renderers/simple_text.py
debts-0.4.dist-info/METADATA
debts-0.4.dist-info/WHEEL
debts-0.4.dist-info/entry_points.txt
debts-0.4.dist-info/top_level.txt
debts-0.4.dist-info/RECORD
