Metadata-Version: 2.1
Name: debts
Version: 0.4
Summary: Help solve debts settlement.
Home-page: https://framagit.org/almet/debts
Author: Alexis Métaireau & contributors
Author-email: alexis@notmyidea.org
License: Custom BSD Beerware
Keywords: debts settlement money balance
Platform: UNKNOWN
Classifier: Programming Language :: Python :: 3.7
Requires-Dist: jinja2
